envedit/__init__.py
envedit/cli.py
envedit/env_parser.py
envedit/tui.py
pyenvedit-0.2.0.dist-info/licenses/LICENSE
pyenvedit-0.2.0.dist-info/METADATA
pyenvedit-0.2.0.dist-info/WHEEL
pyenvedit-0.2.0.dist-info/entry_points.txt
pyenvedit-0.2.0.dist-info/top_level.txt
pyenvedit-0.2.0.dist-info/RECORD
