Metadata-Version: 2.4
Name: pyenvedit
Version: 0.2.0
Summary: A CLI tool for editing .env files with an intuitive interface
Project-URL: Homepage, https://github.com/marcokotrotsos/envedit
Project-URL: Issues, https://github.com/marcokotrotsos/envedit/issues
Classifier: Development Status :: 4 - Beta
Classifier: Intended Audience :: Developers
Classifier: License :: OSI Approved :: MIT License
Classifier: Operating System :: OS Independent
Classifier: Programming Language :: Python :: 3
Classifier: Programming Language :: Python :: 3.8
Classifier: Programming Language :: Python :: 3.9
Classifier: Programming Language :: Python :: 3.10
Classifier: Programming Language :: Python :: 3.11
Classifier: Programming Language :: Python :: 3.12
Requires-Python: >=3.8
License-File: LICENSE
Requires-Dist: textual>=0.40.0
Requires-Dist: click>=8.0.0
Dynamic: license-file
